cargo_venv/__init__.py
cargo_venv/main/__init__.py
cargo_venv/main/main.py
cargo_venv/main/templates/__init__.py
cargo_venv/main/templates/activate
cargo_venv/main/templates/activate.csh
cargo_venv/main/templates/activate.fish
cargo_venv-0.0.6.dist-info/LICENSE
cargo_venv-0.0.6.dist-info/METADATA
cargo_venv-0.0.6.dist-info/WHEEL
cargo_venv-0.0.6.dist-info/entry_points.txt
cargo_venv-0.0.6.dist-info/top_level.txt
cargo_venv-0.0.6.dist-info/RECORD
