Metadata-Version: 2.1
Name: cargo-venv
Version: 0.0.6
Summary: Cargo Virtual Environment
Home-page: https://github.com/dragosdumitrache/cargo-venv
Author: Dragos Dumitrache
Author-email: dragos@afterburner.dev
License: UNKNOWN
Project-URL: Bug Reports, https://github.com/dragosdumitrache/cargo-venv/issues
Project-URL: Source, https://github.com/dragosdumitrache/cargo-venv/
Keywords: git user access management
Platform: UNKNOWN
Classifier: Development Status :: 4 - Beta
Classifier: Intended Audience :: Developers
Classifier: Topic :: Software Development :: Build Tools
Classifier: License :: OSI Approved :: MIT License
Classifier: Programming Language :: Python :: 3
Classifier: Programming Language :: Python :: 3.5
Classifier: Programming Language :: Python :: 3.6
Classifier: Programming Language :: Python :: 3.7
Classifier: Programming Language :: Python :: 3.8
Requires-Python: >=3.7
Requires-Dist: Click
